labdata/__init__.py
labdata/cli.py
labdata/copy.py
labdata/export.py
labdata/s3.py
labdata/stacks.py
labdata/utils.py
labdata/widgets.py
labdata/compute/__init__.py
labdata/compute/caiman.py
labdata/compute/ec2.py
labdata/compute/ephys.py
labdata/compute/pose.py
labdata/compute/schedulers.py
labdata/compute/singularity.py
labdata/compute/suite2p.py
labdata/compute/utils.py
labdata/dashboard/__init__.py
labdata/dashboard/compute.py
labdata/dashboard/decisiontask.py
labdata/dashboard/index.py
labdata/dashboard/segmentation.py
labdata/dashboard/sorting.py
labdata/dashboard/video.py
labdata/dashboard/explorer/__init__.py
labdata/dashboard/explorer/cellsegmentation.py
labdata/dashboard/explorer/spikesorting.py
labdata/rules/__init__.py
labdata/rules/ephys.py
labdata/rules/imaging.py
labdata/rules/utils.py
labdata/schema/__init__.py
labdata/schema/ephys.py
labdata/schema/general.py
labdata/schema/histology.py
labdata/schema/onephoton.py
labdata/schema/procedures.py
labdata/schema/tasks.py
labdata/schema/twophoton.py
labdata/schema/utils.py
labdata/schema/video.py
labdata-0.0.21.dist-info/licenses/LICENSE
labdata-0.0.21.dist-info/METADATA
labdata-0.0.21.dist-info/WHEEL
labdata-0.0.21.dist-info/entry_points.txt
labdata-0.0.21.dist-info/top_level.txt
labdata-0.0.21.dist-info/RECORD
