Metadata-Version: 2.4
Name: labdata
Version: 0.0.21
Summary: Package to manage data in experimental neuroscience labs
Author-email: Joao Couto <jpcouto@gmail.com>
Project-URL: Homepage, https://github.com/jcouto/labdata
Project-URL: Issues, https://github.com/jcouto/labdata/issues
Classifier: Programming Language :: Python :: 3
Classifier: Operating System :: OS Independent
Requires-Python: >=3.0
License-File: LICENSE
Requires-Dist: datajoint
Requires-Dist: boto3
Requires-Dist: tqdm
Requires-Dist: safe-exit
Requires-Dist: joblib>=1.4.0
Requires-Dist: natsort
Requires-Dist: pandas
Requires-Dist: cryptography
Provides-Extra: dashboard
Requires-Dist: dash; extra == "dashboard"
Requires-Dist: dash_bootstrap_components; extra == "dashboard"
Requires-Dist: dash-extensions; extra == "dashboard"
Requires-Dist: plotly; extra == "dashboard"
Requires-Dist: streamlit>1.34; extra == "dashboard"
Requires-Dist: streamlit-bokeh; extra == "dashboard"
Requires-Dist: scipy; extra == "dashboard"
Requires-Dist: scikit-image; extra == "dashboard"
Dynamic: license-file
